gqlauth/__init__.py
gqlauth/admin.py
gqlauth/apps.py
gqlauth/models.py
gqlauth/py.typed
gqlauth/settings.py
gqlauth/settings_type.py
gqlauth/captcha/__init__.py
gqlauth/captcha/captcha_factorty.py
gqlauth/captcha/create.py
gqlauth/captcha/models.py
gqlauth/captcha/types_.py
gqlauth/captcha/fonts/Nehama.ttf
gqlauth/captcha/fonts/OpenSans-Semibold.ttf
gqlauth/captcha/fonts/pltwide.ttf
gqlauth/captcha/fonts/stam.ttf
gqlauth/core/__init__.py
gqlauth/core/constants.py
gqlauth/core/directives.py
gqlauth/core/exceptions.py
gqlauth/core/interfaces.py
gqlauth/core/middlewares.py
gqlauth/core/mixins.py
gqlauth/core/scalars.py
gqlauth/core/types_.py
gqlauth/core/utils.py
gqlauth/jwt/__init__.py
gqlauth/jwt/tools.py
gqlauth/jwt/types_.py
gqlauth/migrations/0001_initial.py
gqlauth/migrations/0002_alter_userstatus_options.py
gqlauth/migrations/0003_delete_captcha.py
gqlauth/migrations/0004_captcha.py
gqlauth/migrations/__init__.py
gqlauth/templates/email/activation_email.html
gqlauth/templates/email/activation_subject.txt
gqlauth/templates/email/password_reset_email.html
gqlauth/templates/email/password_reset_subject.txt
gqlauth/templates/email/password_set_email.html
gqlauth/templates/email/password_set_subject.txt
gqlauth/templates/email/images/gd4f267f778b22183ca1ded4dfae871eac04faaac23286dc27d9c228034ff735042cebd167fb684c47ea3bef8803094f5683f08a3728911b4b191f82a7c12de99_1280.jpg
gqlauth/templates/email/images/windrader-wind-power-fichtelberg-wind-park.jpg
gqlauth/user/__init__.py
gqlauth/user/arg_mutations.py
gqlauth/user/forms.py
gqlauth/user/helpers.py
gqlauth/user/queries.py
gqlauth/user/relay.py
gqlauth/user/resolvers.py
gqlauth/user/signals.py
gqlauth/user/types_.py
gqlauth/user/views.py
strawberry_django_auth-0.378.3.dist-info/METADATA
strawberry_django_auth-0.378.3.dist-info/WHEEL
strawberry_django_auth-0.378.3.dist-info/licenses/LICENSE
strawberry_django_auth-0.378.3.dist-info/RECORD
