Metadata-Version: 2.3
Name: strawberry-django-auth
Version: 0.378.3
Summary: Graphql authentication system with Strawberry for Django.
Project-URL: Documentation, https://nrbnlulu.github.io/strawberry-django-auth/
Project-URL: Homepage, https://github.com/nrbnlulu/strawberry-django-auth
Author-email: Nir Benlulu <nrbnlulu@gmail.com>
Maintainer-email: Nir Benlulu <nrbnlulu@gmail.com>
Classifier: Environment :: Web Environment
Classifier: Framework :: Django
Classifier: Intended Audience :: Developers
Classifier: License :: OSI Approved :: MIT License
Classifier: Operating System :: OS Independent
Classifier: Programming Language :: Python :: 3.10
Classifier: Programming Language :: Python :: 3.11
Classifier: Programming Language :: Python :: 3.12
Requires-Python: <3.14,>=3.10
Requires-Dist: django-stubs[compatible-mypy]>=4.2.0
Requires-Dist: django<5.3,>=4.2
Requires-Dist: django>=5.1.3
Requires-Dist: pyjwt<3.0,>=2.6.0
Requires-Dist: strawberry-graphql-django>=0.47.0
Provides-Extra: captcha
Requires-Dist: pillow>=11.0.0; extra == 'captcha'
